{
    "books": {
        "book1": {
            "name": "1919",
            "description": "A book description",
            "genre": [
                "trending",
                "horror",
                "high-rated"
            ],
            "image": "/assets/images/books/1919.jpg",
            "price": 140,
            "rating": 4.5,
            "reviews": [
                {
                    "user": "mahmoudalaa",
                    "userImage": "/assets/images/users/mahmoudalaa.jpg",
                    "rating": 4,
                    "description": "very nice book, you should read it.",
                    "likes": 42
                },
                {
                    "user": "loai",
                    "userImage": "/assets/images/users/loai.jpg",
                    "rating": 1,
                    "description": "very bad book, don't read.",
                    "likes": 5
                }
            ],
            "author": "ahmed_mourad"
        },
        "book2": {
            "name": "1919",
            "description": "A book description",
            "genre": [
                "trending",
                "drama",
                "high-rated"
            ],
            "image": "/assets/images/books/1919.png",
            "price": 140,
            "rating": 4.5,
            "reviews": [
                {
                    "user": "mahmoudalaa",
                    "userImage": "/assets/images/users/mahmoudalaa.jpg",
                    "rating": 4,
                    "description": "very nice book, you should read it.",
                    "likes": 28
                },
                {
                    "user": "loai",
                    "userImage": "/assets/images/users/loai.jpg",
                    "rating": 1,
                    "description": "very bad book, don't read.",
                    "likes": 3
                }
            ],
            "author": "ahmed_mourad"
        },
        "book3": {
            "name": "1919",
            "description": "A book description",
            "genre": [
                "trending",
                "fantasy",
                "high-rated"
            ],
            "image": "/assets/images/books/1919.png",
            "price": 140,
            "rating": 4.5,
            "reviews": [
                {
                    "user": "mahmoudalaa",
                    "userImage": "/assets/images/users/mahmoudalaa.jpg",
                    "rating": 4,
                    "description": "very nice book, you should read it.",
                    "likes": 67
                },
                {
                    "user": "loai",
                    "userImage": "/assets/images/users/loai.jpg",
                    "rating": 1,
                    "description": "very bad book, don't read.",
                    "likes": 12
                }
            ],
            "author": "ahmed_mourad"
        }
    },
    "authors": {
        "ahmed_mourad": {
            "name": "Ahmed Mourad",
            "age": 45,
            "image": "/assets/images/authors/ahmed_mourad.jpg",
            "books": [
                "book1",
                "book2",
                "book3"
            ]
        }
    }
}